feedzai_altair_theme/__init__.py
feedzai_altair_theme/py.typed
feedzai_altair_theme/theme.py
feedzai_altair_theme/tokens.py
feedzai_altair_theme/types.py
feedzai_altair_theme-2.0.0.dist-info/licenses/LICENSE
feedzai_altair_theme-2.0.0.dist-info/WHEEL
feedzai_altair_theme-2.0.0.dist-info/entry_points.txt
feedzai_altair_theme-2.0.0.dist-info/METADATA
feedzai_altair_theme-2.0.0.dist-info/RECORD
