Metadata-Version: 2.4
Name: feedzai-altair-theme
Version: 2.0.0
Summary: Feedzai's theme for Altair charts.
Keywords: altair,theme,data,visualization
Author: Feedzai
Author-email: Feedzai <oss-licenses@feedzai.com>
License-Expression: Apache-2.0
License-File: LICENSE
Classifier: Development Status :: 5 - Production/Stable
Classifier: Intended Audience :: Developers
Classifier: Intended Audience :: Information Technology
Classifier: Intended Audience :: Science/Research
Classifier: Natural Language :: English
Classifier: Operating System :: OS Independent
Classifier: Programming Language :: Python
Classifier: Programming Language :: Python :: 3
Classifier: Programming Language :: Python :: 3 :: Only
Classifier: Programming Language :: Python :: 3.10
Classifier: Programming Language :: Python :: 3.11
Classifier: Programming Language :: Python :: 3.12
Classifier: Programming Language :: Python :: 3.13
Classifier: Programming Language :: Python :: Implementation :: CPython
Classifier: Topic :: Scientific/Engineering :: Visualization
Classifier: Topic :: Utilities
Classifier: Typing :: Typed
Requires-Dist: altair>=5.5.0
Requires-Python: >=3.10
Project-URL: Changelog, https://github.com/feedzai/feedzai-altair-theme/blob/master/CHANGELOG.md
Project-URL: Issues, https://github.com/feedzai/feedzai-altair-theme/issues
Project-URL: Source, https://github.com/feedzai/feedzai-altair-theme
